{
  "interactionModel": {
    "languageModel": {
      "invocationName": "appalachian trail facts",
      "intents": [
        {
          "name": "AMAZON.CancelIntent",
          "samples": []
        },
        {
          "name": "AMAZON.HelpIntent",
          "samples": []
        },
        {
          "name": "AMAZON.StopIntent",
          "samples": []
        },
        {
          "name": "GetNewFactIntent",
          "samples": [
            "a fact",
            "an appalchian trail fact",
            "tell me a fact",
            "tell me an appalachian trail fact",
            "give me a fact",
            "give me an appalachian trail fact",
            "tell me trivia",
            "tell me an appalachian trail trivia",
            "give me trivia",
            "give me an appalachian trail trivia",
            "give me some information",
            "give me some appalachian trail information",
            "tell me something",
            "give me something"
          ],
          "slots": []
        }
      ]
    }
  }
}
